weatherxu/__init__.py
weatherxu/client.py
weatherxu/models.py
weatherxu-1.0.1.dist-info/METADATA
weatherxu-1.0.1.dist-info/WHEEL
weatherxu-1.0.1.dist-info/top_level.txt
weatherxu-1.0.1.dist-info/RECORD
