Metadata-Version: 2.2
Name: weatherxu
Version: 1.0.1
Summary: Official Python SDK for weatherxu.com
Home-page: https://github.com/weatherxu/weatherxu-python
Author: WeatherXu
Author-email: contact@weatherxu.com
Keywords: weather,weather data,weather forecast,weather api
Dynamic: author
Dynamic: author-email
Dynamic: description
Dynamic: description-content-type
Dynamic: home-page
Dynamic: keywords
Dynamic: summary
